imRender/__init__.py
imRender/annLblShow/__init__.py
imRender/annLblShow/labelmeRender.py
imRender-0.1.1.dist-info/LICENSE
imRender-0.1.1.dist-info/METADATA
imRender-0.1.1.dist-info/WHEEL
imRender-0.1.1.dist-info/top_level.txt
imRender-0.1.1.dist-info/RECORD
