Metadata-Version: 2.1
Name: imRender
Version: 0.1.1
Summary: .
License: Apache-2.0
Project-URL: Github, https://github.com/firstelfin/imRender
Classifier: Programming Language :: Python :: 3
Requires-Python: >=3.10
License-File: LICENSE
Requires-Dist: loguru (>=0.7.2)
Requires-Dist: tqdm
Requires-Dist: pillow
Requires-Dist: opencv-python
